Metadata-Version: 2.4
Name: kfac-jax
Version: 0.0.7
Summary: A Jax package for approximate curvature estimation and optimization using KFAC.
Author-email: DeepMind <kfac-jax-dev@google.com>
License: 
Project-URL: Repository, https://github.com/google-deepmind/kfac-jax
Classifier: Development Status :: 4 - Beta
Classifier: Intended Audience :: Developers
Classifier: Intended Audience :: Education
Classifier: Intended Audience :: Science/Research
Classifier: License :: OSI Approved :: Apache Software License
Classifier: Programming Language :: Python :: 3
Classifier: Programming Language :: Python :: 3.10
Classifier: Programming Language :: Python :: 3.11
Classifier: Topic :: Scientific/Engineering :: Artificial Intelligence
Classifier: Topic :: Scientific/Engineering :: Mathematics
Classifier: Topic :: Software Development :: Libraries
Classifier: Topic :: Software Development :: Libraries :: Python Modules
Requires-Python: >=3.10
License-File: LICENSE
Requires-Dist: absl-py>=0.12.0
Requires-Dist: immutabledict>=2.2.1
Requires-Dist: numpy>=1.22
Requires-Dist: distrax>=0.1.3
Requires-Dist: jax>=0.4.27
Requires-Dist: jaxlib>=0.4.27
Requires-Dist: dm-tree>=0.1.7
Requires-Dist: optax>=0.1.4
Requires-Dist: typing-extensions>=4.0.0
Provides-Extra: docs
Requires-Dist: sphinx>=5.3.0; extra == "docs"
Requires-Dist: sphinx_rtd_theme>=1.3.0; extra == "docs"
Requires-Dist: sphinxcontrib-katex>=0.9.7; extra == "docs"
Requires-Dist: sphinxcontrib-bibtex>=2.6.1; extra == "docs"
Requires-Dist: sphinx-autodoc-typehints>=1.20.0; extra == "docs"
Requires-Dist: pandoc>=2.3; extra == "docs"
Requires-Dist: IPython>=8.10.0; extra == "docs"
Requires-Dist: ipykernel>=5.3.4; extra == "docs"
Requires-Dist: myst_nb>=0.17.2; extra == "docs"
Requires-Dist: docutils>=0.17.0; extra == "docs"
Requires-Dist: matplotlib>=3.5.0; extra == "docs"
Provides-Extra: examples
Requires-Dist: ml_collections>=0.1.1; extra == "examples"
Requires-Dist: optax>=0.1.1; extra == "examples"
Requires-Dist: dm-haiku>=0.0.6; extra == "examples"
Requires-Dist: jaxline>=0.0.5; extra == "examples"
Requires-Dist: tensorflow>=2.8.0; extra == "examples"
Requires-Dist: tensorflow_datasets>=4.5.2; extra == "examples"
Provides-Extra: tests
Requires-Dist: pytest-xdist; extra == "tests"
Requires-Dist: absl-py>=0.12.0; extra == "tests"
Requires-Dist: immutabledict>=2.2.1; extra == "tests"
Requires-Dist: numpy>=1.22; extra == "tests"
Requires-Dist: distrax>=0.1.3; extra == "tests"
Requires-Dist: jax>=0.6.0; extra == "tests"
Requires-Dist: jaxlib>=0.4.27; extra == "tests"
Requires-Dist: dm-haiku>=0.0.9; extra == "tests"
Requires-Dist: dm-tree>=0.1.7; extra == "tests"
Requires-Dist: optax>=0.1.4; extra == "tests"
Dynamic: license-file
